kanjidb/__init__.py
kanjidb/__main__.py
kanjidb/__version__.py
kanjidb/dumper.py
kanjidb/encoding.py
kanjidb/loader.py
kanjidb/main.py
kanjidb/builder/__init__.py
kanjidb/builder/configuration.py
kanjidb/builder/plugins/__init__.py
kanjidb/builder/plugins/helloworld.py
kanjidb/builder/plugins/jsonstream.py
kanjidb/builder/plugins/jsonwriter.py
kanjidb/builder/plugins/kanjidic2.py
kanjidb/builder/plugins/kanjistream.py
kanjidb/builder/plugins/kanjivg.py
kanjidb/builder/plugins/mergedict.py
kanjidb/service/__init__.py
kanjidb/service/app.py
kanjidb/service/configuration.py
kanjidb/service/main.py
test/__init__.py
test/test_builder.py
test/test_encoding.py
test/test_loader.py
test/test_plugins_helloworld.py
test/test_plugins_jsonstream.py
test/test_plugins_jsonwriter.py
test/test_plugins_kanjidic2.py
test/test_plugins_kanjistream.py
test/test_plugins_mergedict.py
test/test_sample_generatedb.py
test/test_service.py
kanjidb-0.1a2.dist-info/LICENSE
kanjidb-0.1a2.dist-info/METADATA
kanjidb-0.1a2.dist-info/WHEEL
kanjidb-0.1a2.dist-info/top_level.txt
kanjidb-0.1a2.dist-info/RECORD
