Metadata-Version: 2.1
Name: kanjidb
Version: 0.1a2
Summary: Kanji Database
Home-page: https://github.com/Nauja/kanjidb
Author: Jeremy Morosi
Author-email: jeremymorosi@hotmail.com
License: UNKNOWN
Project-URL: Bug Tracker, https://github.com/Nauja/kanjidb/issues
Project-URL: Source Code, https://github.com/Nauja/kanjidb/
Platform: UNKNOWN
Classifier: Development Status :: 3 - Alpha
Classifier: Intended Audience :: Developers
Classifier: Topic :: Software Development :: Build Tools
Classifier: Programming Language :: Python :: 3.6
Classifier: Programming Language :: Python :: 3.7
Classifier: Programming Language :: Python :: 3.8
Requires-Python: >=3.6
Requires-Dist: aiohttp
Requires-Dist: aiohttp-cors
Requires-Dist: aiohttp-swagger
Requires-Dist: jamdict (>=0.1a6)
Requires-Dist: pyyaml
